reducss/__init__.py
reducss/reducss.py
reducss-1.2.1.dist-info/LICENSE
reducss-1.2.1.dist-info/METADATA
reducss-1.2.1.dist-info/WHEEL
reducss-1.2.1.dist-info/top_level.txt
reducss-1.2.1.dist-info/RECORD
