Metadata-Version: 2.1
Name: reducss
Version: 1.2.1
Summary: simple & flexible SSG
Home-page: https://github.com/laddge/reducss
Author: Laddge
Author-email: dev.laddge@gmail.com
License: MIT
Platform: UNKNOWN
Requires-Dist: beautifulsoup4 (>=4.5.0)
